configplusplus/__init__.py
configplusplus/base.py
configplusplus/env_loader.py
configplusplus/utils.py
configplusplus/yaml_loader.py
configplusplus-0.1.0.dist-info/METADATA
configplusplus-0.1.0.dist-info/WHEEL
configplusplus-0.1.0.dist-info/licenses/LICENSE
configplusplus-0.1.0.dist-info/RECORD
