Metadata-Version: 2.4
Name: configplusplus
Version: 0.1.0
Summary: A powerful configuration management library with beautiful display, environment variables and YAML support
License: MIT
License-File: LICENSE
Keywords: config,configuration,environment,yaml,settings
Author: Florian BARRE
Requires-Python: >=3.10,<4.0
Classifier: Development Status :: 4 - Beta
Classifier: Intended Audience :: Developers
Classifier: License :: OSI Approved :: MIT License
Classifier: Programming Language :: Python :: 3
Classifier: Programming Language :: Python :: 3.10
Classifier: Programming Language :: Python :: 3.11
Classifier: Programming Language :: Python :: 3.12
Classifier: Programming Language :: Python :: 3.13
Classifier: Programming Language :: Python :: 3.14
Classifier: Topic :: Software Development :: Libraries :: Python Modules
Requires-Dist: loggerplusplus (>=1.0.5)
Requires-Dist: python-dotenv (>=1.0.0,<2.0.0)
Requires-Dist: pyyaml (>=6.0.1,<7.0.0)
Project-URL: Documentation, https://github.com/Florian-BARRE/ConfigPlusPlus#readme
Project-URL: Homepage, https://github.com/Florian-BARRE/ConfigPlusPlus
Project-URL: Repository, https://github.com/Florian-BARRE/ConfigPlusPlus
